ai_code_review_tool/__init__.py
ai_code_review_tool/chunk_file.py
ai_code_review_tool/cli.py
ai_code_review_tool/generate_patches.py
ai_code_review_tool/generate_roadmap.py
ai_code_review_tool/get_code_review_suggestions.py
ai_code_review_tool/git_utils.py
ai_code_review_tool/learning_tracker.py
ai_code_review_tool/openai_integration.py
ai_code_review_tool/project_explainer.py
ai_code_review_tool/release.py
ai_code_review_tool/requirements_updater.py
ai_code_review_tool/snapshot_tool.py
ai_code_review_tool/troubleshoot_code_errors.py
ai_code_review_tool/version_utils.py
ai_code_review_tool/walk_and_review_project.py
ai_code_review_tool/walk_project.py
ai_code_review_tool-1.0.0rc8.dist-info/METADATA
ai_code_review_tool-1.0.0rc8.dist-info/WHEEL
ai_code_review_tool-1.0.0rc8.dist-info/entry_points.txt
ai_code_review_tool-1.0.0rc8.dist-info/top_level.txt
ai_code_review_tool-1.0.0rc8.dist-info/RECORD
